Workbook
Name Slicer_Region: #N/A
Name Slicer_Segment: #N/A
Name Slicer_Year: #N/A

Sheet KPI YOY
A3: Row Labels | B3: Sum of Sales | C3: Sum of Profit | D3: Sum of Quantity | E3: Count of Order ID | F3: profit margin
A4: 2011 | B4: 484247.5 | C4: 49543.974 | D4: 7581 | E4: 1993 | F4: 0.10231126
A5: 2012 | B5: 470532.51 | C5: 61618.604 | D5: 7979 | E5: 2102 | F5: 0.13095504
A6: 2013 | B6: 608473.83 | C6: 81726.931 | D6: 9810 | E6: 2580 | F6: 0.13431462
A7: 2014 | B7: 733947.02 | C7: 93507.513 | D7: 12503 | E7: 3319 | F7: 0.12740363
H9: =GETPIVOTDATA("[Measures].[Sum of Sales]",$A$3,"[Table_1].[Year]","[Table_1].[Year].&[2014]")/GETPIVOTDATA("[Measures].[Sum of Sales]",$A$3,"[Table_1].[Year]","[Table_1].[Year].&[2013]")-1 -> 0.20620968 | I9: =GETPIVOTDATA("[Measures].[Sum of Profit]",$A$3,"[Table_1].[Year]","[Table_1].[Year].&[2014]")/GETPIVOTDATA("[Measures].[Sum of Profit]",$A$3,"[Table_1].[Year]","[Table_1].[Year].&[2013]")-1 -> 0.14414566 | J9: =GETPIVOTDATA("[Measures].[Sum of Quantity]",$A$3,"[Table_1].[Year]","[Table_1].[Year].&[2014]")/GETPIVOTDATA("[Measures].[Sum of Quantity]",$A$3,"[Table_1].[Year]","[Table_1].[Year].&[2013]")-1 -> 0.2745158 | K9: =GETPIVOTDATA("[Measures].[Count of Order ID]",$A$3,"[Table_1].[Year]","[Table_1].[Year].&[2014]")/GETPIVOTDATA("[Measures].[Count of Order ID]",$A$3,"[Table_1].[Year]","[Table_1].[Year].&[2013]")-1 -> 0.28643411 | L9: =GETPIVOTDATA("[Measures].[profit margin]",$A$3,"[Table_1].[Year]","[Table_1].[Year].&[2014]")/GETPIVOTDATA("[Measures].[profit margin]",$A$3,"[Table_1].[Year]","[Table_1].[Year].&[2013]")-1 -> -0.051453757

Sheet Data
A1: Row ID | B1: Order ID | C1: Year | D1: Order Date | E1: Ship Date | F1: Ship Mode | G1: Customer ID | H1: Customer Name | I1: Segment | J1: Country | K1: City | L1: State | M1: Postal Code | N1: Region | O1: Product ID | P1: Category | Q1: Sub-Category | R1: Product Name | S1: Sales | T1: Quantity | U1: Discount | V1: Profit | W1: profit_margin
A2: 1 | B2: CA-2013-152156 | C2: =YEAR(Data!$D2) -> 2013 | D2: 41587 | E2: 41590 | F2: Second Class | G2: CG-12520 | H2: Claire Gute | I2: Consumer | J2: United States | K2: Henderson | L2: Kentucky | M2: 42420 | N2: South | O2: FUR-BO-10001798 | P2: Furniture | Q2: Bookcases | R2: Bush Somerset Collection Bookcase | S2: 261.96 | T2: 2 | U2: 0 | V2: 41.9136
A3: 2 | B3: CA-2013-152156 | C3: =YEAR(Data!$D3) -> 2013 | D3: 41587 | E3: 41590 | F3: Second Class | G3: CG-12520 | H3: Claire Gute | I3: Consumer | J3: United States | K3: Henderson | L3: Kentucky | M3: 42420 | N3: South | O3: FUR-CH-10000454 | P3: Furniture | Q3: Chairs | R3: Hon Deluxe Fabric Upholstered Stacking Chairs, Rounded Back | S3: 731.94 | T3: 3 | U3: 0 | V3: 219.582
A4: 3 | B4: CA-2013-138688 | C4: =YEAR(Data!$D4) -> 2013 | D4: 41438 | E4: 41442 | F4: Second Class | G4: DV-13045 | H4: Darrin Van Huff | I4: Corporate | J4: United States | K4: Los Angeles | L4: California | M4: 90036 | N4: West | O4: OFF-LA-10000240 | P4: Office Supplies | Q4: Labels | R4: Self-Adhesive Address Labels for Typewriters by Universal | S4: 14.62 | T4: 2 | U4: 0 | V4: 6.8714 | W4: =Table_1[[#This Row],[Profit]]/Table_1[[#This Row],[Sales]] -> 0.47
A5: 4 | B5: US-2012-108966 | C5: =YEAR(Data!$D5) -> 2012 | D5: 41193 | E5: 41200 | F5: Standard Class | G5: SO-20335 | H5: Sean O'Donnell | I5: Consumer | J5: United States | K5: Fort Lauderdale | L5: Florida | M5: 33311 | N5: South | O5: FUR-TA-10000577 | P5: Furniture | Q5: Tables | R5: Bretford CR4500 Series Slim Rectangular Table | S5: 957.5775 | T5: 5 | U5: 0.45 | V5: -383.031
A6: 5 | B6: US-2012-108966 | C6: =YEAR(Data!$D6) -> 2012 | D6: 41193 | E6: 41200 | F6: Standard Class | G6: SO-20335 | H6: Sean O'Donnell | I6: Consumer | J6: United States | K6: Fort Lauderdale | L6: Florida | M6: 33311 | N6: South | O6: OFF-ST-10000760 | P6: Office Supplies | Q6: Storage | R6: Eldon Fold 'N Roll Cart System | S6: 22.368 | T6: 2 | U6: 0.2 | V6: 2.5164
A7: 6 | B7: CA-2011-115812 | C7: =YEAR(Data!$D7) -> 2011 | D7: 40703 | E7: 40708 | F7: Standard Class | G7: BH-11710 | H7: Brosina Hoffman | I7: Consumer | J7: United States | K7: Los Angeles | L7: California | M7: 90032 | N7: West | O7: FUR-FU-10001487 | P7: Furniture | Q7: Furnishings | R7: Eldon Expressions Wood and Plastic Desk Accessories, Cherry Wood | S7: 48.86 | T7: 7 | U7: 0 | V7: 14.1694 | W7: =Table_1[[#This Row],[Profit]]/Table_1[[#This Row],[Sales]] -> 0.29
A8: 7 | B8: CA-2011-115812 | C8: =YEAR(Data!$D8) -> 2011 | D8: 40703 | E8: 40708 | F8: Standard Class | G8: BH-11710 | H8: Brosina Hoffman | I8: Consumer | J8: United States | K8: Los Angeles | L8: California | M8: 90032 | N8: West | O8: OFF-AR-10002833 | P8: Office Supplies | Q8: Art | R8: Newell 322 | S8: 7.28 | T8: 4 | U8: 0 | V8: 1.9656 | W8: =Table_1[[#This Row],[Profit]]/Table_1[[#This Row],[Sales]] -> 0.27
A9: 8 | B9: CA-2011-115812 | C9: =YEAR(Data!$D9) -> 2011 | D9: 40703 | E9: 40708 | F9: Standard Class | G9: BH-11710 | H9: Brosina Hoffman | I9: Consumer | J9: United States | K9: Los Angeles | L9: California | M9: 90032 | N9: West | O9: TEC-PH-10002275 | P9: Technology | Q9: Phones | R9: Mitel 5320 IP Phone VoIP phone | S9: 907.152 | T9: 6 | U9: 0.2 | V9: 90.7152 | W9: =Table_1[[#This Row],[Profit]]/Table_1[[#This Row],[Sales]] -> 0.1
A10: 9 | B10: CA-2011-115812 | C10: =YEAR(Data!$D10) -> 2011 | D10: 40703 | E10: 40708 | F10: Standard Class | G10: BH-11710 | H10: Brosina Hoffman | I10: Consumer | J10: United States | K10: Los Angeles | L10: California | M10: 90032 | N10: West | O10: OFF-BI-10003910 | P10: Office Supplies | Q10: Binders | R10: DXL Angle-View Binders with Locking Rings by Samsill | S10: 18.504 | T10: 3 | U10: 0.2 | V10: 5.7825 | W10: =Table_1[[#This Row],[Profit]]/Table_1[[#This Row],[Sales]] -> 0.3125
A11: 10 | B11: CA-2011-115812 | C11: =YEAR(Data!$D11) -> 2011 | D11: 40703 | E11: 40708 | F11: Standard Class | G11: BH-11710 | H11: Brosina Hoffman | I11: Consumer | J11: United States | K11: Los Angeles | L11: California | M11: 90032 | N11: West | O11: OFF-AP-10002892 | P11: Office Supplies | Q11: Appliances | R11: Belkin F5C206VTEL 6 Outlet Surge | S11: 114.9 | T11: 5 | U11: 0 | V11: 34.47 | W11: =Table_1[[#This Row],[Profit]]/Table_1[[#This Row],[Sales]] -> 0.3
A12: 11 | B12: CA-2011-115812 | C12: =YEAR(Data!$D12) -> 2011 | D12: 40703 | E12: 40708 | F12: Standard Class | G12: BH-11710 | H12: Brosina Hoffman | I12: Consumer | J12: United States | K12: Los Angeles | L12: California | M12: 90032 | N12: West | O12: FUR-TA-10001539 | P12: Furniture | Q12: Tables | R12: Chromcraft Rectangular Conference Tables | S12: 1706.184 | T12: 9 | U12: 0.2 | V12: 85.3092 | W12: =Table_1[[#This Row],[Profit]]/Table_1[[#This Row],[Sales]] -> 0.05
A13: 12 | B13: CA-2011-115812 | C13: =YEAR(Data!$D13) -> 2011 | D13: 40703 | E13: 40708 | F13: Standard Class | G13: BH-11710 | H13: Brosina Hoffman | I13: Consumer | J13: United States | K13: Los Angeles | L13: California | M13: 90032 | N13: West | O13: TEC-PH-10002033 | P13: Technology | Q13: Phones | R13: Konftel 250 Conference phone - Charcoal black | S13: 911.424 | T13: 4 | U13: 0.2 | V13: 68.3568 | W13: =Table_1[[#This Row],[Profit]]/Table_1[[#This Row],[Sales]] -> 0.075
A14: 13 | B14: CA-2014-114412 | C14: =YEAR(Data!$D14) -> 2014 | D14: 41745 | E14: 41750 | F14: Standard Class | G14: AA-10480 | H14: Andrew Allen | I14: Consumer | J14: United States | K14: Concord | L14: North Carolina | M14: 28027 | N14: South | O14: OFF-PA-10002365 | P14: Office Supplies | Q14: Paper | R14: Xerox 1967 | S14: 15.552 | T14: 3 | U14: 0.2 | V14: 5.4432
A15: 14 | B15: CA-2013-161389 | C15: =YEAR(Data!$D15) -> 2013 | D15: 41614 | E15: 41619 | F15: Standard Class | G15: IM-15070 | H15: Irene Maddox | I15: Consumer | J15: United States | K15: Seattle | L15: Washington | M15: 98103 | N15: West | O15: OFF-BI-10003656 | P15: Office Supplies | Q15: Binders | R15: Fellowes PB200 Plastic Comb Binding Machine | S15: 407.976 | T15: 3 | U15: 0.2 | V15: 132.5922 | W15: =Table_1[[#This Row],[Profit]]/Table_1[[#This Row],[Sales]] -> 0.325
A16: 15 | B16: US-2012-118983 | C16: =YEAR(Data!$D16) -> 2012 | D16: 41235 | E16: 41239 | F16: Standard Class | G16: HP-14815 | H16: Harold Pawlan | I16: Home Office | J16: United States | K16: Fort Worth | L16: Texas | M16: 76106 | N16: Central | O16: OFF-AP-10002311 | P16: Office Supplies | Q16: Appliances | R16: Holmes Replacement Filter for HEPA Air Cleaner, Very Large Room, HEPA Filter | S16: 68.81 | T16: 5 | U16: 0.8 | V16: -123.858
A17: 16 | B17: US-2012-118983 | C17: =YEAR(Data!$D17) -> 2012 | D17: 41235 | E17: 41239 | F17: Standard Class | G17: HP-14815 | H17: Harold Pawlan | I17: Home Office | J17: United States | K17: Fort Worth | L17: Texas | M17: 76106 | N17: Central | O17: OFF-BI-10000756 | P17: Office Supplies | Q17: Binders | R17: Storex DuraTech Recycled Plastic Frosted Binders | S17: 2.544 | T17: 3 | U17: 0.8 | V17: -3.816
A18: 17 | B18: CA-2011-105893 | C18: =YEAR(Data!$D18) -> 2011 | D18: 40858 | E18: 40865 | F18: Standard Class | G18: PK-19075 | H18: Pete Kriz | I18: Consumer | J18: United States | K18: Madison | L18: Wisconsin | M18: 53711 | N18: Central | O18: OFF-ST-10004186 | P18: Office Supplies | Q18: Storage | R18: Stur-D-Stor Shelving, Vertical 5-Shelf: 72"H x 36"W x 18 1/2"D | S18: 665.88 | T18: 6 | U18: 0 | V18: 13.3176
A19: 18 | B19: CA-2011-167164 | C19: =YEAR(Data!$D19) -> 2011 | D19: 40676 | E19: 40678 | F19: Second Class | G19: AG-10270 | H19: Alejandro Grove | I19: Consumer | J19: United States | K19: West Jordan | L19: Utah | M19: 84084 | N19: West | O19: OFF-ST-10000107 | P19: Office Supplies | Q19: Storage | R19: Fellowes Super Stor/Drawer | S19: 55.5 | T19: 2 | U19: 0 | V19: 9.99 | W19: =Table_1[[#This Row],[Profit]]/Table_1[[#This Row],[Sales]] -> 0.18
A20: 19 | B20: CA-2011-143336 | C20: =YEAR(Data!$D20) -> 2011 | D20: 40782 | E20: 40787 | F20: Second Class | G20: ZD-21925 | H20: Zuschuss Donatelli | I20: Consumer | J20: United States | K20: San Francisco | L20: California | M20: 94109 | N20: West | O20: OFF-AR-10003056 | P20: Office Supplies | Q20: Art | R20: Newell 341 | S20: 8.56 | T20: 2 | U20: 0 | V20: 2.4824 | W20: =Table_1[[#This Row],[Profit]]/Table_1[[#This Row],[Sales]] -> 0.29
A21: 20 | B21: CA-2011-143336 | C21: =YEAR(Data!$D21) -> 2011 | D21: 40782 | E21: 40787 | F21: Second Class | G21: ZD-21925 | H21: Zuschuss Donatelli | I21: Consumer | J21: United States | K21: San Francisco | L21: California | M21: 94109 | N21: West | O21: TEC-PH-10001949 | P21: Technology | Q21: Phones | R21: Cisco SPA 501G IP Phone | S21: 213.48 | T21: 3 | U21: 0.2 | V21: 16.011 | W21: =Table_1[[#This Row],[Profit]]/Table_1[[#This Row],[Sales]] -> 0.075
A22: 21 | B22: CA-2011-143336 | C22: =YEAR(Data!$D22) -> 2011 | D22: 40782 | E22: 40787 | F22: Second Class | G22: ZD-21925 | H22: Zuschuss Donatelli | I22: Consumer | J22: United States | K22: San Francisco | L22: California | M22: 94109 | N22: West | O22: OFF-BI-10002215 | P22: Office Supplies | Q22: Binders | R22: Wilson Jones Hanging View Binder, White, 1" | S22: 22.72 | T22: 4 | U22: 0.2 | V22: 7.384 | W22: =Table_1[[#This Row],[Profit]]/Table_1[[#This Row],[Sales]] -> 0.325
A23: 22 | B23: CA-2013-137330 | C23: =YEAR(Data!$D23) -> 2013 | D23: 41618 | E23: 41622 | F23: Standard Class | G23: KB-16585 | H23: Ken Black | I23: Corporate | J23: United States | K23: Fremont | L23: Nebraska | M23: 68025 | N23: Central | O23: OFF-AR-10000246 | P23: Office Supplies | Q23: Art | R23: Newell 318 | S23: 19.46 | T23: 7 | U23: 0 | V23: 5.0596
A24: 23 | B24: CA-2013-137330 | C24: =YEAR(Data!$D24) -> 2013 | D24: 41618 | E24: 41622 | F24: Standard Class | G24: KB-16585 | H24: Ken Black | I24: Corporate | J24: United States | K24: Fremont | L24: Nebraska | M24: 68025 | N24: Central | O24: OFF-AP-10001492 | P24: Office Supplies | Q24: Appliances | R24: Acco Six-Outlet Power Strip, 4' Cord Length | S24: 60.34 | T24: 7 | U24: 0 | V24: 15.6884
A25: 24 | B25: US-2014-156909 | C25: =YEAR(Data!$D25) -> 2014 | D25: 41837 | E25: 41839 | F25: Second Class | G25: SF-20065 | H25: Sandra Flanagan | I25: Consumer | J25: United States | K25: Philadelphia | L25: Pennsylvania | M25: 19140 | N25: East | O25: FUR-CH-10002774 | P25: Furniture | Q25: Chairs | R25: Global Deluxe Stacking Chair, Gray | S25: 71.372 | T25: 2 | U25: 0.3 | V25: -1.0196
A26: 25 | B26: CA-2012-106320 | C26: =YEAR(Data!$D26) -> 2012 | D26: 41177 | E26: 41182 | F26: Standard Class | G26: EB-13870 | H26: Emily Burns | I26: Consumer | J26: United States | K26: Orem | L26: Utah | M26: 84057 | N26: West | O26: FUR-TA-10000577 | P26: Furniture | Q26: Tables | R26: Bretford CR4500 Series Slim Rectangular Table | S26: 1044.63 | T26: 3 | U26: 0 | V26: 240.2649 | W26: =Table_1[[#This Row],[Profit]]/Table_1[[#This Row],[Sales]] -> 0.23
A27: 26 | B27: CA-2013-121755 | C27: =YEAR(Data!$D27) -> 2013 | D27: 41290 | E27: 41294 | F27: Second Class | G27: EH-13945 | H27: Eric Hoffmann | I27: Consumer | J27: United States | K27: Los Angeles | L27: California | M27: 90049 | N27: West | O27: OFF-BI-10001634 | P27: Office Supplies | Q27: Binders | R27: Wilson Jones Active Use Binders | S27: 11.648 | T27: 2 | U27: 0.2 | V27: 4.2224 | W27: =Table_1[[#This Row],[Profit]]/Table_1[[#This Row],[Sales]] -> 0.3625
A28: 27 | B28: CA-2013-121755 | C28: =YEAR(Data!$D28) -> 2013 | D28: 41290 | E28: 41294 | F28: Second Class | G28: EH-13945 | H28: Eric Hoffmann | I28: Consumer | J28: United States | K28: Los Angeles | L28: California | M28: 90049 | N28: West | O28: TEC-AC-10003027 | P28: Technology | Q28: Accessories | R28: Imation 8GB Mini TravelDrive USB 2.0 Flash Drive | S28: 90.57 | T28: 3 | U28: 0 | V28: 11.7741 | W28: =Table_1[[#This Row],[Profit]]/Table_1[[#This Row],[Sales]] -> 0.13
A29: 28 | B29: US-2012-150630 | C29: =YEAR(Data!$D29) -> 2012 | D29: 41169 | E29: 41173 | F29: Standard Class | G29: TB-21520 | H29: Tracy Blumstein | I29: Consumer | J29: United States | K29: Philadelphia | L29: Pennsylvania | M29: 19140 | N29: East | O29: FUR-BO-10004834 | P29: Furniture | Q29: Bookcases | R29: Riverside Palais Royal Lawyers Bookcase, Royale Cherry Finish | S29: 3083.43 | T29: 7 | U29: 0.5 | V29: -1665.0522
A30: 29 | B30: US-2012-150630 | C30: =YEAR(Data!$D30) -> 2012 | D30: 41169 | E30: 41173 | F30: Standard Class | G30: TB-21520 | H30: Tracy Blumstein | I30: Consumer | J30: United States | K30: Philadelphia | L30: Pennsylvania | M30: 19140 | N30: East | O30: OFF-BI-10000474 | P30: Office Supplies | Q30: Binders | R30: Avery Recycled Flexi-View Covers for Binding Systems | S30: 9.618 | T30: 2 | U30: 0.7 | V30: -7.0532
A31: 30 | B31: US-2012-150630 | C31: =YEAR(Data!$D31) -> 2012 | D31: 41169 | E31: 41173 | F31: Standard Class | G31: TB-21520 | H31: Tracy Blumstein | I31: Consumer | J31: United States | K31: Philadelphia | L31: Pennsylvania | M31: 19140 | N31: East | O31: FUR-FU-10004848 | P31: Furniture | Q31: Furnishings | R31: Howard Miller 13-3/4" Diameter Brushed Chrome Round Wall Clock | S31: 124.2 | T31: 3 | U31: 0.2 | V31: 15.525
A32: 31 | B32: US-2012-150630 | C32: =YEAR(Data!$D32) -> 2012 | D32: 41169 | E32: 41173 | F32: Standard Class | G32: TB-21520 | H32: Tracy Blumstein | I32: Consumer | J32: United States | K32: Philadelphia | L32: Pennsylvania | M32: 19140 | N32: East | O32: OFF-EN-10001509 | P32: Office Supplies | Q32: Envelopes | R32: Poly String Tie Envelopes | S32: 3.264 | T32: 2 | U32: 0.2 | V32: 1.1016
A33: 32 | B33: US-2012-150630 | C33: =YEAR(Data!$D33) -> 2012 | D33: 41169 | E33: 41173 | F33: Standard Class | G33: TB-21520 | H33: Tracy Blumstein | I33: Consumer | J33: United States | K33: Philadelphia | L33: Pennsylvania | M33: 19140 | N33: East | O33: OFF-AR-10004042 | P33: Office Supplies | Q33: Art | R33: BOSTON Model 1800 Electric Pencil Sharpeners, Putty/Woodgrain | S33: 86.304 | T33: 6 | U33: 0.2 | V33: 9.7092
A34: 33 | B34: US-2012-150630 | C34: =YEAR(Data!$D34) -> 2012 | D34: 41169 | E34: 41173 | F34: Standard Class | G34: TB-21520 | H34: Tracy Blumstein | I34: Consumer | J34: United States | K34: Philadelphia | L34: Pennsylvania | M34: 19140 | N34: East | O34: OFF-BI-10001525 | P34: Office Supplies | Q34: Binders | R34: Acco Pressboard Covers with Storage Hooks, 14 7/8" x 11", Executive Red | S34: 6.858 | T34: 6 | U34: 0.7 | V34: -5.715
A35: 34 | B35: US-2012-150630 | C35: =YEAR(Data!$D35) -> 2012 | D35: 41169 | E35: 41173 | F35: Standard Class | G35: TB-21520 | H35: Tracy Blumstein | I35: Consumer | J35: United States | K35: Philadelphia | L35: Pennsylvania | M35: 19140 | N35: East | O35: OFF-AR-10001683 | P35: Office Supplies | Q35: Art | R35: Lumber Crayons | S35: 15.76 | T35: 2 | U35: 0.2 | V35: 3.546
A36: 35 | B36: CA-2014-107727 | C36: =YEAR(Data!$D36) -> 2014 | D36: 41932 | E36: 41936 | F36: Second Class | G36: MA-17560 | H36: Matt Abelman | I36: Home Office | J36: United States | K36: Houston | L36: Texas | M36: 77095 | N36: Central | O36: OFF-PA-10000249 | P36: Office Supplies | Q36: Paper | R36: Staples | S36: 29.472 | T36: 3 | U36: 0.2 | V36: 9.9468
A37: 36 | B37: CA-2013-117590 | C37: =YEAR(Data!$D37) -> 2013 | D37: 41617 | E37: 41619 | F37: First Class | G37: GH-14485 | H37: Gene Hale | I37: Corporate | J37: United States | K37: Richardson | L37: Texas | M37: 75080 | N37: Central | O37: TEC-PH-10004977 | P37: Technology | Q37: Phones | R37: GE 30524EE4 | S37: 1097.544 | T37: 7 | U37: 0.2 | V37: 123.4737
A38: 37 | B38: CA-2013-117590 | C38: =YEAR(Data!$D38) -> 2013 | D38: 41617 | E38: 41619 | F38: First Class | G38: GH-14485 | H38: Gene Hale | I38: Corporate | J38: United States | K38: Richardson | L38: Texas | M38: 75080 | N38: Central | O38: FUR-FU-10003664 | P38: Furniture | Q38: Furnishings | R38: Electrix Architect's Clamp-On Swing Arm Lamp, Black | S38: 190.92 | T38: 5 | U38: 0.6 | V38: -147.963
A39: 38 | B39: CA-2012-117415 | C39: =YEAR(Data!$D39) -> 2012 | D39: 41270 | E39: 41274 | F39: Standard Class | G39: SN-20710 | H39: Steve Nguyen | I39: Home Office | J39: United States | K39: Houston | L39: Texas | M39: 77041 | N39: Central | O39: OFF-EN-10002986 | P39: Office Supplies | Q39: Envelopes | R39: #10-4 1/8" x 9 1/2" Premium Diagonal Seam Envelopes | S39: 113.328 | T39: 9 | U39: 0.2 | V39: 35.415
A40: 39 | B40: CA-2012-117415 | C40: =YEAR(Data!$D40) -> 2012 | D40: 41270 | E40: 41274 | F40: Standard Class | G40: SN-20710 | H40: Steve Nguyen | I40: Home Office | J40: United States | K40: Houston | L40: Texas | M40: 77041 | N40: Central | O40: FUR-BO-10002545 | P40: Furniture | Q40: Bookcases | R40: Atlantic Metals Mobile 3-Shelf Bookcases, Custom Colors | S40: 532.3992 | T40: 3 | U40: 0.32 | V40: -46.9764
... A43: 42 | B43: CA-2014-120999 | C43: =YEAR(Data!$D43) -> 2014 | D43: 41893 | E43: 41898 | F43: Standard Class | G43: LC-16930 | H43: Linda Cazamias | I43: Corporate | J43: United States | K43: Naperville | L43: Illinois | M43: 60540 | N43: Central | O43: TEC-PH-10004093 | P43: Technology | Q43: Phones | R43: Panasonic Kx-TS550 | S43: 147.168 | T43: 4 | U43: 0.2 | V43: 16.5564
A44: 43 | B44: CA-2013-101343 | C44: =YEAR(Data!$D44) -> 2013 | D44: 41473 | E44: 41478 | F44: Standard Class | G44: RA-19885 | H44: Ruben Ausman | I44: Corporate | J44: United States | K44: Los Angeles | L44: California | M44: 90049 | N44: West | O44: OFF-ST-10003479 | P44: Office Supplies | Q44: Storage | R44: Eldon Base for stackable storage shelf, platinum | S44: 77.88 | T44: 2 | U44: 0 | V44: 3.894 | W44: =Table_1[[#This Row],[Profit]]/Table_1[[#This Row],[Sales]] -> 0.05
A45: 44 | B45: CA-2014-139619 | C45: =YEAR(Data!$D45) -> 2014 | D45: 41902 | E45: 41906 | F45: Standard Class | G45: ES-14080 | H45: Erin Smith | I45: Corporate | J45: United States | K45: Melbourne | L45: Florida | M45: 32935 | N45: South | O45: OFF-ST-10003282 | P45: Office Supplies | Q45: Storage | R45: Advantus 10-Drawer Portable Organizer, Chrome Metal Frame, Smoke Drawers | S45: 95.616 | T45: 2 | U45: 0.2 | V45: 9.5616
A46: 45 | B46: CA-2013-118255 | C46: =YEAR(Data!$D46) -> 2013 | D46: 41345 | E46: 41347 | F46: First Class | G46: ON-18715 | H46: Odella Nelson | I46: Corporate | J46: United States | K46: Eagan | L46: Minnesota | M46: 55122 | N46: Central | O46: TEC-AC-10000171 | P46: Technology | Q46: Accessories | R46: Verbatim 25 GB 6x Blu-ray Single Layer Recordable Disc, 25/Pack | S46: 45.98 | T46: 2 | U46: 0 | V46: 19.7714
A47: 46 | B47: CA-2013-118255 | C47: =YEAR(Data!$D47) -> 2013 | D47: 41345 | E47: 41347 | F47: First Class | G47: ON-18715 | H47: Odella Nelson | I47: Corporate | J47: United States | K47: Eagan | L47: Minnesota | M47: 55122 | N47: Central | O47: OFF-BI-10003291 | P47: Office Supplies | Q47: Binders | R47: Wilson Jones Leather-Like Binders with DublLock Round Rings | S47: 17.46 | T47: 2 | U47: 0 | V47: 8.2062
A48: 47 | B48: CA-2011-146703 | C48: =YEAR(Data!$D48) -> 2011 | D48: 40836 | E48: 40841 | F48: Second Class | G48: PO-18865 | H48: Patrick O'Donnell | I48: Consumer | J48: United States | K48: Westland | L48: Michigan | M48: 48185 | N48: Central | O48: OFF-ST-10001713 | P48: Office Supplies | Q48: Storage | R48: Gould Plastics 9-Pocket Panel Bin, 18-3/8w x 5-1/4d x 20-1/2h, Black | S48: 211.96 | T48: 4 | U48: 0 | V48: 8.4784
A49: 48 | B49: CA-2013-169194 | C49: =YEAR(Data!$D49) -> 2013 | D49: 41446 | E49: 41451 | F49: Standard Class | G49: LH-16900 | H49: Lena Hernandez | I49: Consumer | J49: United States | K49: Dover | L49: Delaware | M49: 19901 | N49: East | O49: TEC-AC-10002167 | P49: Technology | Q49: Accessories | R49: Imation 8gb Micro Traveldrive Usb 2.0 Flash Drive | S49: 45 | T49: 3 | U49: 0 | V49: 4.95
A50: 49 | B50: CA-2013-169194 | C50: =YEAR(Data!$D50) -> 2013 | D50: 41446 | E50: 41451 | F50: Standard Class | G50: LH-16900 | H50: Lena Hernandez | I50: Consumer | J50: United States | K50: Dover | L50: Delaware | M50: 19901 | N50: East | O50: TEC-PH-10003988 | P50: Technology | Q50: Phones | R50: LF Elite 3D Dazzle Designer Hard Case Cover, Lf Stylus Pen and Wiper For Apple Iphone 5c Mini Lite | S50: 21.8 | T50: 2 | U50: 0 | V50: 6.104
A51: 50 | B51: CA-2012-115742 | C51: =YEAR(Data!$D51) -> 2012 | D51: 41017 | E51: 41021 | F51: Standard Class | G51: DP-13000 | H51: Darren Powers | I51: Consumer | J51: United States | K51: New Albany | L51: Indiana | M51: 47150 | N51: Central | O51: OFF-BI-10004410 | P51: Office Supplies | Q51: Binders | R51: C-Line Peel & Stick Add-On Filing Pockets, 8-3/4 x 5-1/8, 10/Pack | S51: 38.22 | T51: 6 | U51: 0 | V51: 17.9634
A52: 51 | B52: CA-2012-115742 | C52: =YEAR(Data!$D52) -> 2012 | D52: 41017 | E52: 41021 | F52: Standard Class | G52: DP-13000 | H52: Darren Powers | I52: Consumer | J52: United States | K52: New Albany | L52: Indiana | M52: 47150 | N52: Central | O52: OFF-LA-10002762 | P52: Office Supplies | Q52: Labels | R52: Avery 485 | S52: 75.18 | T52: 6 | U52: 0 | V52: 35.3346
A53: 52 | B53: CA-2012-115742 | C53: =YEAR(Data!$D53) -> 2012 | D53: 41017 | E53: 41021 | F53: Standard Class | G53: DP-13000 | H53: Darren Powers | I53: Consumer | J53: United States | K53: New Albany | L53: Indiana | M53: 47150 | N53: Central | O53: FUR-FU-10001706 | P53: Furniture | Q53: Furnishings | R53: Longer-Life Soft White Bulbs | S53: 6.16 | T53: 2 | U53: 0 | V53: 2.9568
A54: 53 | B54: CA-2012-115742 | C54: =YEAR(Data!$D54) -> 2012 | D54: 41017 | E54: 41021 | F54: Standard Class | G54: DP-13000 | H54: Darren Powers | I54: Consumer | J54: United States | K54: New Albany | L54: Indiana | M54: 47150 | N54: Central | O54: FUR-CH-10003061 | P54: Furniture | Q54: Chairs | R54: Global Leather Task Chair, Black | S54: 89.99 | T54: 1 | U54: 0 | V54: 17.0981
A55: 54 | B55: CA-2013-105816 | C55: =YEAR(Data!$D55) -> 2013 | D55: 41620 | E55: 41626 | F55: Standard Class | G55: JM-15265 | H55: Janet Molinari | I55: Corporate | J55: United States | K55: New York City | L55: New York | M55: 10024 | N55: East | O55: OFF-FA-10000304 | P55: Office Supplies | Q55: Fasteners | R55: Advantus Push Pins | S55: 15.26 | T55: 7 | U55: 0 | V55: 6.2566
A56: 55 | B56: CA-2013-105816 | C56: =YEAR(Data!$D56) -> 2013 | D56: 41620 | E56: 41626 | F56: Standard Class | G56: JM-15265 | H56: Janet Molinari | I56: Corporate | J56: United States | K56: New York City | L56: New York | M56: 10024 | N56: East | O56: TEC-PH-10002447 | P56: Technology | Q56: Phones | R56: AT&T CL83451 4-Handset Telephone | S56: 1029.95 | T56: 5 | U56: 0 | V56: 298.6855
... A63: 62 | B63: CA-2013-111682 | C63: =YEAR(Data!$D63) -> 2013 | D63: 41443 | E63: 41444 | F63: First Class | G63: TB-21055 | H63: Ted Butterfield | I63: Consumer | J63: United States | K63: Troy | L63: New York | M63: 12180 | N63: East | O63: OFF-AR-10001868 | P63: Office Supplies | Q63: Art | R63: Prang Dustless Chalk Sticks | S63: 1.68 | T63: 1 | U63: 0 | V63: 0.84
A64: 63 | B64: CA-2012-135545 | C64: =YEAR(Data!$D64) -> 2012 | D64: 41237 | E64: 41243 | F64: Standard Class | G64: KM-16720 | H64: Kunst Miller | I64: Consumer | J64: United States | K64: Los Angeles | L64: California | M64: 90004 | N64: West | O64: TEC-AC-10004633 | P64: Technology | Q64: Accessories | R64: Verbatim 25 GB 6x Blu-ray Single Layer Recordable Disc, 3/Pack | S64: 13.98 | T64: 2 | U64: 0 | V64: 6.1512 | W64: =Table_1[[#This Row],[Profit]]/Table_1[[#This Row],[Sales]] -> 0.44
A65: 64 | B65: CA-2012-135545 | C65: =YEAR(Data!$D65) -> 2012 | D65: 41237 | E65: 41243 | F65: Standard Class | G65: KM-16720 | H65: Kunst Miller | I65: Consumer | J65: United States | K65: Los Angeles | L65: California | M65: 90004 | N65: West | O65: OFF-BI-10001078 | P65: Office Supplies | Q65: Binders | R65: Acco PRESSTEX Data Binder with Storage Hooks, Dark Blue, 14 7/8" X 11" | S65: 25.824 | T65: 6 | U65: 0.2 | V65: 9.3612 | W65: =Table_1[[#This Row],[Profit]]/Table_1[[#This Row],[Sales]] -> 0.3625
A66: 65 | B66: CA-2012-135545 | C66: =YEAR(Data!$D66) -> 2012 | D66: 41237 | E66: 41243 | F66: Standard Class | G66: KM-16720 | H66: Kunst Miller | I66: Consumer | J66: United States | K66: Los Angeles | L66: California | M66: 90004 | N66: West | O66: OFF-PA-10003892 | P66: Office Supplies | Q66: Paper | R66: Xerox 1943 | S66: 146.73 | T66: 3 | U66: 0 | V66: 68.9631 | W66: =Table_1[[#This Row],[Profit]]/Table_1[[#This Row],[Sales]] -> 0.47
A67: 66 | B67: CA-2012-135545 | C67: =YEAR(Data!$D67) -> 2012 | D67: 41237 | E67: 41243 | F67: Standard Class | G67: KM-16720 | H67: Kunst Miller | I67: Consumer | J67: United States | K67: Los Angeles | L67: California | M67: 90004 | N67: West | O67: FUR-FU-10000397 | P67: Furniture | Q67: Furnishings | R67: Luxo Economy Swing Arm Lamp | S67: 79.76 | T67: 4 | U67: 0 | V67: 22.3328 | W67: =Table_1[[#This Row],[Profit]]/Table_1[[#This Row],[Sales]] -> 0.28
A68: 67 | B68: US-2012-164175 | C68: =YEAR(Data!$D68) -> 2012 | D68: 41029 | E68: 41034 | F68: Standard Class | G68: PS-18970 | H68: Paul Stevenson | I68: Home Office | J68: United States | K68: Chicago | L68: Illinois | M68: 60610 | N68: Central | O68: FUR-CH-10001146 | P68: Furniture | Q68: Chairs | R68: Global Value Mid-Back Manager's Chair, Gray | S68: 213.115 | T68: 5 | U68: 0.3 | V68: -15.2225
A69: 68 | B69: CA-2011-106376 | C69: =YEAR(Data!$D69) -> 2011 | D69: 40882 | E69: 40887 | F69: Standard Class | G69: BS-11590 | H69: Brendan Sweed | I69: Corporate | J69: United States | K69: Gilbert | L69: Arizona | M69: 85234 | N69: West | O69: OFF-AR-10002671 | P69: Office Supplies | Q69: Art | R69: Hunt BOSTON Model 1606 High-Volume Electric Pencil Sharpener, Beige | S69: 1113.024 | T69: 8 | U69: 0.2 | V69: 111.3024 | W69: =Table_1[[#This Row],[Profit]]/Table_1[[#This Row],[Sales]] -> 0.1
A70: 69 | B70: CA-2011-106376 | C70: =YEAR(Data!$D70) -> 2011 | D70: 40882 | E70: 40887 | F70: Standard Class | G70: BS-11590 | H70: Brendan Sweed | I70: Corporate | J70: United States | K70: Gilbert | L70: Arizona | M70: 85234 | N70: West | O70: TEC-PH-10002726 | P70: Technology | Q70: Phones | R70: netTALK DUO VoIP Telephone Service | S70: 167.968 | T70: 4 | U70: 0.2 | V70: 62.988 | W70: =Table_1[[#This Row],[Profit]]/Table_1[[#This Row],[Sales]] -> 0.375
A71: 70 | B71: CA-2013-119823 | C71: =YEAR(Data!$D71) -> 2013 | D71: 41430 | E71: 41432 | F71: First Class | G71: KD-16270 | H71: Karen Daniels | I71: Consumer | J71: United States | K71: Springfield | L71: Virginia | M71: 22153 | N71: South | O71: OFF-PA-10000482 | P71: Office Supplies | Q71: Paper | R71: Snap-A-Way Black Print Carbonless Ruled Speed Letter, Triplicate | S71: 75.88 | T71: 2 | U71: 0 | V71: 35.6636
A72: 71 | B72: CA-2013-106075 | C72: =YEAR(Data!$D72) -> 2013 | D72: 41536 | E72: 41541 | F72: Standard Class | G72: HM-14980 | H72: Henry MacAllister | I72: Consumer | J72: United States | K72: New York City | L72: New York | M72: 10009 | N72: East | O72: OFF-BI-10004654 | P72: Office Supplies | Q72: Binders | R72: Avery Binding System Hidden Tab Executive Style Index Sets | S72: 4.616 | T72: 1 | U72: 0.2 | V72: 1.731
A73: 72 | B73: CA-2014-114440 | C73: =YEAR(Data!$D73) -> 2014 | D73: 41897 | E73: 41900 | F73: Second Class | G73: TB-21520 | H73: Tracy Blumstein | I73: Consumer | J73: United States | K73: Jackson | L73: Michigan | M73: 49201 | N73: Central | O73: OFF-PA-10004675 | P73: Office Supplies | Q73: Paper | R73: Telephone Message Books with Fax/Mobile Section, 5 1/2" x 3 3/16" | S73: 19.05 | T73: 3 | U73: 0 | V73: 8.763
A74: 73 | B74: US-2012-134026 | C74: =YEAR(Data!$D74) -> 2012 | D74: 41025 | E74: 41031 | F74: Standard Class | G74: JE-15745 | H74: Joel Eaton | I74: Consumer | J74: United States | K74: Memphis | L74: Tennessee | M74: 38109 | N74: South | O74: FUR-CH-10000513 | P74: Furniture | Q74: Chairs | R74: High-Back Leather Manager's Chair | S74: 831.936 | T74: 8 | U74: 0.2 | V74: -114.3912
A75: 74 | B75: US-2012-134026 | C75: =YEAR(Data!$D75) -> 2012 | D75: 41025 | E75: 41031 | F75: Standard Class | G75: JE-15745 | H75: Joel Eaton | I75: Consumer | J75: United States | K75: Memphis | L75: Tennessee | M75: 38109 | N75: South | O75: FUR-FU-10003708 | P75: Furniture | Q75: Furnishings | R75: Tenex Traditional Chairmats for Medium Pile Carpet, Standard Lip, 36" x 48" | S75: 97.04 | T75: 2 | U75: 0.2 | V75: 1.213
A76: 75 | B76: US-2012-134026 | C76: =YEAR(Data!$D76) -> 2012 | D76: 41025 | E76: 41031 | F76: Standard Class | G76: JE-15745 | H76: Joel Eaton | I76: Consumer | J76: United States | K76: Memphis | L76: Tennessee | M76: 38109 | N76: South | O76: OFF-ST-10004123 | P76: Office Supplies | Q76: Storage | R76: Safco Industrial Wire Shelving System | S76: 72.784 | T76: 1 | U76: 0.2 | V76: -18.196
A77: 76 | B77: US-2014-118038 | C77: =YEAR(Data!$D77) -> 2014 | D77: 41983 | E77: 41985 | F77: First Class | G77: KB-16600 | H77: Ken Brennan | I77: Corporate | J77: United States | K77: Houston | L77: Texas | M77: 77041 | N77: Central | O77: OFF-BI-10004182 | P77: Office Supplies | Q77: Binders | R77: Economy Binders | S77: 1.248 | T77: 3 | U77: 0.8 | V77: -1.9344
A78: 77 | B78: US-2014-118038 | C78: =YEAR(Data!$D78) -> 2014 | D78: 41983 | E78: 41985 | F78: First Class | G78: KB-16600 | H78: Ken Brennan | I78: Corporate | J78: United States | K78: Houston | L78: Texas | M78: 77041 | N78: Central | O78: FUR-FU-10000260 | P78: Furniture | Q78: Furnishings | R78: 6" Cubicle Wall Clock, Black | S78: 9.708 | T78: 3 | U78: 0.6 | V78: -5.8248
A79: 78 | B79: US-2014-118038 | C79: =YEAR(Data!$D79) -> 2014 | D79: 41983 | E79: 41985 | F79: First Class | G79: KB-16600 | H79: Ken Brennan | I79: Corporate | J79: United States | K79: Houston | L79: Texas | M79: 77041 | N79: Central | O79: OFF-ST-10000615 | P79: Office Supplies | Q79: Storage | R79: SimpliFile Personal File, Black Granite, 15w x 6-15/16d x 11-1/4h | S79: 27.24 | T79: 3 | U79: 0.2 | V79: 2.724
A80: 79 | B80: US-2011-147606 | C80: =YEAR(Data!$D80) -> 2011 | D80: 40873 | E80: 40878 | F80: Second Class | G80: JE-15745 | H80: Joel Eaton | I80: Consumer | J80: United States | K80: Houston | L80: Texas | M80: 77070 | N80: Central | O80: FUR-FU-10003194 | P80: Furniture | Q80: Furnishings | R80: Eldon Expressions Desk Accessory, Wood Pencil Holder, Oak | S80: 19.3 | T80: 5 | U80: 0.6 | V80: -14.475
A81: 80 | B81: CA-2013-127208 | C81: =YEAR(Data!$D81) -> 2013 | D81: 41438 | E81: 41441 | F81: First Class | G81: SC-20770 | H81: Stewart Carmichael | I81: Corporate | J81: United States | K81: Decatur | L81: Alabama | M81: 35601 | N81: South | O81: OFF-AP-10002118 | P81: Office Supplies | Q81: Appliances | R81: 1.7 Cubic Foot Compact "Cube" Office Refrigerators | S81: 208.16 | T81: 1 | U81: 0 | V81: 56.2032
A82: 81 | B82: CA-2013-127208 | C82: =YEAR(Data!$D82) -> 2013 | D82: 41438 | E82: 41441 | F82: First Class | G82: SC-20770 | H82: Stewart Carmichael | I82: Corporate | J82: United States | K82: Decatur | L82: Alabama | M82: 35601 | N82: South | O82: OFF-BI-10002309 | P82: Office Supplies | Q82: Binders | R82: Avery Heavy-Duty EZD Binder With Locking Rings | S82: 16.74 | T82: 3 | U82: 0 | V82: 8.0352
A83: 82 | B83: CA-2011-139451 | C83: =YEAR(Data!$D83) -> 2011 | D83: 40828 | E83: 40832 | F83: Standard Class | G83: DN-13690 | H83: Duane Noonan | I83: Consumer | J83: United States | K83: San Francisco | L83: California | M83: 94122 | N83: West | O83: OFF-AR-10002053 | P83: Office Supplies | Q83: Art | R83: Premium Writing Pencils, Soft, #2 by Central Association for the Blind | S83: 14.9 | T83: 5 | U83: 0 | V83: 4.172 | W83: =Table_1[[#This Row],[Profit]]/Table_1[[#This Row],[Sales]] -> 0.28
A84: 83 | B84: CA-2011-139451 | C84: =YEAR(Data!$D84) -> 2011 | D84: 40828 | E84: 40832 | F84: Standard Class | G84: DN-13690 | H84: Duane Noonan | I84: Consumer | J84: United States | K84: San Francisco | L84: California | M84: 94122 | N84: West | O84: OFF-ST-10002370 | P84: Office Supplies | Q84: Storage | R84: Sortfiler Multipurpose Personal File Organizer, Black | S84: 21.39 | T84: 1 | U84: 0 | V84: 6.2031 | W84: =Table_1[[#This Row],[Profit]]/Table_1[[#This Row],[Sales]] -> 0.29
A85: 84 | B85: CA-2012-149734 | C85: =YEAR(Data!$D85) -> 2012 | D85: 41155 | E85: 41160 | F85: Standard Class | G85: JC-16105 | H85: Julie Creighton | I85: Corporate | J85: United States | K85: Durham | L85: North Carolina | M85: 27707 | N85: South | O85: OFF-EN-10000927 | P85: Office Supplies | Q85: Envelopes | R85: Jet-Pak Recycled Peel 'N' Seal Padded Mailers | S85: 200.984 | T85: 7 | U85: 0.2 | V85: 62.8075
A86: 85 | B86: US-2014-119662 | C86: =YEAR(Data!$D86) -> 2014 | D86: 41957 | E86: 41960 | F86: First Class | G86: CS-12400 | H86: Christopher Schild | I86: Home Office | J86: United States | K86: Chicago | L86: Illinois | M86: 60623 | N86: Central | O86: OFF-ST-10003656 | P86: Office Supplies | Q86: Storage | R86: Safco Industrial Wire Shelving | S86: 230.376 | T86: 3 | U86: 0.2 | V86: -48.9549
A87: 86 | B87: CA-2014-140088 | C87: =YEAR(Data!$D87) -> 2014 | D87: 41788 | E87: 41790 | F87: Second Class | G87: PO-18865 | H87: Patrick O'Donnell | I87: Consumer | J87: United States | K87: Columbia | L87: South Carolina | M87: 29203 | N87: South | O87: FUR-CH-10000863 | P87: Furniture | Q87: Chairs | R87: Novimex Swivel Fabric Task Chair | S87: 301.96 | T87: 2 | U87: 0 | V87: 33.2156
A88: 87 | B88: CA-2014-155558 | C88: =YEAR(Data!$D88) -> 2014 | D88: 41939 | E88: 41946 | F88: Standard Class | G88: PG-18895 | H88: Paul Gonzalez | I88: Consumer | J88: United States | K88: Rochester | L88: Minnesota | M88: 55901 | N88: Central | O88: TEC-AC-10001998 | P88: Technology | Q88: Accessories | R88: Logitech LS21 Speaker System - PC Multimedia - 2.1-CH - Wired | S88: 19.99 | T88: 1 | U88: 0 | V88: 6.7966
A89: 88 | B89: CA-2014-155558 | C89: =YEAR(Data!$D89) -> 2014 | D89: 41939 | E89: 41946 | F89: Standard Class | G89: PG-18895 | H89: Paul Gonzalez | I89: Consumer | J89: United States | K89: Rochester | L89: Minnesota | M89: 55901 | N89: Central | O89: OFF-LA-10000134 | P89: Office Supplies | Q89: Labels | R89: Avery 511 | S89: 6.16 | T89: 2 | U89: 0 | V89: 2.9568
A90: 89 | B90: CA-2013-159695 | C90: =YEAR(Data!$D90) -> 2013 | D90: 41370 | E90: 41375 | F90: Second Class | G90: GM-14455 | H90: Gary Mitchum | I90: Home Office | J90: United States | K90: Houston | L90: Texas | M90: 77095 | N90: Central | O90: OFF-ST-10003442 | P90: Office Supplies | Q90: Storage | R90: Eldon Portable Mobile Manager | S90: 158.368 | T90: 7 | U90: 0.2 | V90: 13.8572
A91: 90 | B91: CA-2013-109806 | C91: =YEAR(Data!$D91) -> 2013 | D91: 41535 | E91: 41540 | F91: Standard Class | G91: JS-15685 | H91: Jim Sink | I91: Corporate | J91: United States | K91: Los Angeles | L91: California | M91: 90036 | N91: West | O91: OFF-AR-10004930 | P91: Office Supplies | Q91: Art | R91: Turquoise Lead Holder with Pocket Clip | S91: 20.1 | T91: 3 | U91: 0 | V91: 6.633 | W91: =Table_1[[#This Row],[Profit]]/Table_1[[#This Row],[Sales]] -> 0.33
A92: 91 | B92: CA-2013-109806 | C92: =YEAR(Data!$D92) -> 2013 | D92: 41535 | E92: 41540 | F92: Standard Class | G92: JS-15685 | H92: Jim Sink | I92: Corporate | J92: United States | K92: Los Angeles | L92: California | M92: 90036 | N92: West | O92: TEC-PH-10004093 | P92: Technology | Q92: Phones | R92: Panasonic Kx-TS550 | S92: 73.584 | T92: 2 | U92: 0.2 | V92: 8.2782 | W92: =Table_1[[#This Row],[Profit]]/Table_1[[#This Row],[Sales]] -> 0.1125
A93: 92 | B93: CA-2013-109806 | C93: =YEAR(Data!$D93) -> 2013 | D93: 41535 | E93: 41540 | F93: Standard Class | G93: JS-15685 | H93: Jim Sink | I93: Corporate | J93: United States | K93: Los Angeles | L93: California | M93: 90036 | N93: West | O93: OFF-PA-10000304 | P93: Office Supplies | Q93: Paper | R93: Xerox 1995 | S93: 6.48 | T93: 1 | U93: 0 | V93: 3.1104 | W93: =Table_1[[#This Row],[Profit]]/Table_1[[#This Row],[Sales]] -> 0.48
A94: 93 | B94: CA-2012-149587 | C94: =YEAR(Data!$D94) -> 2012 | D94: 40939 | E94: 40944 | F94: Second Class | G94: KB-16315 | H94: Karl Braun | I94: Consumer | J94: United States | K94: Minneapolis | L94: Minnesota | M94: 55407 | N94: Central | O94: OFF-PA-10003177 | P94: Office Supplies | Q94: Paper | R94: Xerox 1999 | S94: 12.96 | T94: 2 | U94: 0 | V94: 6.2208
A95: 94 | B95: CA-2012-149587 | C95: =YEAR(Data!$D95) -> 2012 | D95: 40939 | E95: 40944 | F95: Second Class | G95: KB-16315 | H95: Karl Braun | I95: Consumer | J95: United States | K95: Minneapolis | L95: Minnesota | M95: 55407 | N95: Central | O95: FUR-FU-10003799 | P95: Furniture | Q95: Furnishings | R95: Seth Thomas 13 1/2" Wall Clock | S95: 53.34 | T95: 3 | U95: 0 | V95: 16.5354
A96: 95 | B96: CA-2012-149587 | C96: =YEAR(Data!$D96) -> 2012 | D96: 40939 | E96: 40944 | F96: Second Class | G96: KB-16315 | H96: Karl Braun | I96: Consumer | J96: United States | K96: Minneapolis | L96: Minnesota | M96: 55407 | N96: Central | O96: OFF-BI-10002852 | P96: Office Supplies | Q96: Binders | R96: Ibico Standard Transparent Covers | S96: 32.96 | T96: 2 | U96: 0 | V96: 16.1504
A97: 96 | B97: US-2014-109484 | C97: =YEAR(Data!$D97) -> 2014 | D97: 41950 | E97: 41956 | F97: Standard Class | G97: RB-19705 | H97: Roger Barcio | I97: Home Office | J97: United States | K97: Portland | L97: Oregon | M97: 97206 | N97: West | O97: OFF-BI-10004738 | P97: Office Supplies | Q97: Binders | R97: Flexible Leather- Look Classic Collection Ring Binder | S97: 5.682 | T97: 1 | U97: 0.7 | V97: -3.788 | W97: =Table_1[[#This Row],[Profit]]/Table_1[[#This Row],[Sales]] -> -0.66666667
A98: 97 | B98: CA-2014-161018 | C98: =YEAR(Data!$D98) -> 2014 | D98: 41953 | E98: 41955 | F98: Second Class | G98: PN-18775 | H98: Parhena Norris | I98: Home Office | J98: United States | K98: New York City | L98: New York | M98: 10009 | N98: East | O98: FUR-FU-10000629 | P98: Furniture | Q98: Furnishings | R98: 9-3/4 Diameter Round Wall Clock | S98: 96.53 | T98: 7 | U98: 0 | V98: 40.5426
A99: 98 | B99: CA-2014-157833 | C99: =YEAR(Data!$D99) -> 2014 | D99: 41808 | E99: 41811 | F99: First Class | G99: KD-16345 | H99: Katherine Ducich | I99: Consumer | J99: United States | K99: San Francisco | L99: California | M99: 94122 | N99: West | O99: OFF-BI-10001721 | P99: Office Supplies | Q99: Binders | R99: Trimflex Flexible Post Binders | S99: 51.312 | T99: 3 | U99: 0.2 | V99: 17.9592 | W99: =Table_1[[#This Row],[Profit]]/Table_1[[#This Row],[Sales]] -> 0.35
A100: 99 | B100: CA-2013-149223 | C100: =YEAR(Data!$D100) -> 2013 | D100: 41524 | E100: 41529 | F100: Standard Class | G100: ER-13855 | H100: Elpida Rittenbach | I100: Corporate | J100: United States | K100: Saint Paul | L100: Minnesota | M100: 55106 | N100: Central | O100: OFF-AP-10000358 | P100: Office Supplies | Q100: Appliances | R100: Fellowes Basic Home/Office Series Surge Protectors | S100: 77.88 | T100: 6 | U100: 0 | V100: 22.5852
A101: 100 | B101: CA-2013-158568 | C101: =YEAR(Data!$D101) -> 2013 | D101: 41516 | E101: 41520 | F101: Standard Class | G101: RB-19465 | H101: Rick Bensley | I101: Home Office | J101: United States | K101: Chicago | L101: Illinois | M101: 60610 | N101: Central | O101: OFF-PA-10003256 | P101: Office Supplies | Q101: Paper | R101: Avery Personal Creations Heavyweight Cards | S101: 64.624 | T101: 7 | U101: 0.2 | V101: 22.6184
A102: 101 | B102: CA-2013-158568 | C102: =YEAR(Data!$D102) -> 2013 | D102: 41516 | E102: 41520 | F102: Standard Class | G102: RB-19465 | H102: Rick Bensley | I102: Home Office | J102: United States | K102: Chicago | L102: Illinois | M102: 60610 | N102: Central | O102: TEC-AC-10001767 | P102: Technology | Q102: Accessories | R102: SanDisk Ultra 64 GB MicroSDHC Class 10 Memory Card | S102: 95.976 | T102: 3 | U102: 0.2 | V102: -10.7973
A103: 102 | B103: CA-2013-158568 | C103: =YEAR(Data!$D103) -> 2013 | D103: 41516 | E103: 41520 | F103: Standard Class | G103: RB-19465 | H103: Rick Bensley | I103: Home Office | J103: United States | K103: Chicago | L103: Illinois | M103: 60610 | N103: Central | O103: OFF-BI-10002609 | P103: Office Supplies | Q103: Binders | R103: Avery Hidden Tab Dividers for Binding Systems | S103: 1.788 | T103: 3 | U103: 0.8 | V103: -3.0396
A104: 103 | B104: CA-2013-129903 | C104: =YEAR(Data!$D104) -> 2013 | D104: 41610 | E104: 41613 | F104: Second Class | G104: GZ-14470 | H104: Gary Zandusky | I104: Consumer | J104: United States | K104: Rochester | L104: Minnesota | M104: 55901 | N104: Central | O104: OFF-PA-10004040 | P104: Office Supplies | Q104: Paper | R104: Universal Premium White Copier/Laser Paper (20Lb. and 87 Bright) | S104: 23.92 | T104: 4 | U104: 0 | V104: 11.7208
A105: 104 | B105: US-2012-156867 | C105: =YEAR(Data!$D105) -> 2012 | D105: 41226 | E105: 41230 | F105: Standard Class | G105: LC-16870 | H105: Lena Cacioppo | I105: Consumer | J105: United States | K105: Aurora | L105: Colorado | M105: 80013 | N105: West | O105: TEC-AC-10001552 | P105: Technology | Q105: Accessories | R105: Logitech K350 2.4Ghz Wireless Keyboard | S105: 238.896 | T105: 6 | U105: 0.2 | V105: -26.8758 | W105: =Table_1[[#This Row],[Profit]]/Table_1[[#This Row],[Sales]] -> -0.1125
A106: 105 | B106: US-2012-156867 | C106: =YEAR(Data!$D106) -> 2012 | D106: 41226 | E106: 41230 | F106: Standard Class | G106: LC-16870 | H106: Lena Cacioppo | I106: Consumer | J106: United States | K106: Aurora | L106: Colorado | M106: 80013 | N106: West | O106: FUR-FU-10004006 | P106: Furniture | Q106: Furnishings | R106: Deflect-o DuraMat Lighweight, Studded, Beveled Mat for Low Pile Carpeting | S106: 102.36 | T106: 3 | U106: 0.2 | V106: -3.8385 | W106: =Table_1[[#This Row],[Profit]]/Table_1[[#This Row],[Sales]] -> -0.0375
A107: 106 | B107: US-2012-156867 | C107: =YEAR(Data!$D107) -> 2012 | D107: 41226 | E107: 41230 | F107: Standard Class | G107: LC-16870 | H107: Lena Cacioppo | I107: Consumer | J107: United States | K107: Aurora | L107: Colorado | M107: 80013 | N107: West | O107: OFF-BI-10002794 | P107: Office Supplies | Q107: Binders | R107: Avery Trapezoid Ring Binder, 3" Capacity, Black, 1040 sheets | S107: 36.882 | T107: 3 | U107: 0.7 | V107: -25.8174 | W107: =Table_1[[#This Row],[Profit]]/Table_1[[#This Row],[Sales]] -> -0.7
A108: 107 | B108: CA-2014-119004 | C108: =YEAR(Data!$D108) -> 2014 | D108: 41967 | E108: 41972 | F108: Standard Class | G108: JM-15250 | H108: Janet Martin | I108: Consumer | J108: United States | K108: Charlotte | L108: North Carolina | M108: 28205 | N108: South | O108: TEC-AC-10003499 | P108: Technology | Q108: Accessories | R108: Memorex Mini Travel Drive 8 GB USB 2.0 Flash Drive | S108: 74.112 | T108: 8 | U108: 0.2 | V108: 17.6016
...

Sheet KPI
A3: Row Labels | B3: Sum of Sales | D3: Row Labels | E3: Sum of Profit | G3: Row Labels | H3: Sum of Quantity | K3: Row Labels | L3: Count of Order ID | N3: Row Labels | O3: profit margin
A4: Jan | B4: 95365.938 | D4: Jan | E4: 9199.27 | G4: Jan | H4: 1500 | K4: Jan | L4: 387 | N4: Jan | O4: 0.096462849
A5: Feb | B5: 60172.649 | D5: Feb | E5: 10288.899 | G5: Feb | H5: 1068 | K5: Feb | L5: 301 | N5: Feb | O5: 0.17098962
A6: Mar | B6: 199252.98 | D6: Mar | E6: 26806.574 | G6: Mar | H6: 2491 | K6: Mar | L6: 680 | N6: Mar | O6: 0.13453537
A7: Apr | B7: 141851.57 | D7: Apr | E7: 13437.807 | G7: Apr | H7: 2441 | K7: Apr | L7: 663 | N7: Apr | O7: 0.094731465
A8: May | B8: 156122.29 | D8: May | E8: 22308.513 | G8: May | H8: 2850 | K8: May | L8: 750 | N8: May | O8: 0.14289128
A9: Jun | B9: 147082.61 | D9: Jun | E9: 20899.335 | G9: Jun | H9: 2644 | K9: Jun | L9: 709 | N9: Jun | O9: 0.14209249
A10: Jul | B10: 149580.84 | D10: Jul | E10: 13535.383 | G10: Jul | H10: 2705 | K10: Jul | L10: 708 | N10: Jul | O10: 0.09048875
A11: Aug | B11: 159589.45 | D11: Aug | E11: 21896.715 | G11: Aug | H11: 2796 | K11: Aug | L11: 710 | N11: Aug | O11: 0.13720653
A12: Sep | B12: 309770.1 | D12: Sep | E12: 37293.193 | G12: Sep | H12: 5073 | K12: Sep | L12: 1386 | N12: Sep | O12: 0.1203899
A13: Oct | B13: 197115.2 | D13: Oct | E13: 31469.664 | G13: Oct | H13: 3095 | K13: Oct | L13: 817 | N13: Oct | O13: 0.15965113
A14: Nov | B14: 349120.07 | D14: Nov | E14: 35825.537 | G14: Nov | H14: 5741 | K14: Nov | L14: 1462 | N14: Nov | O14: 0.10261666
A15: Dec | B15: 332177.16 | D15: Dec | E15: 43436.134 | G15: Dec | H15: 5469 | K15: Dec | L15: 1421 | N15: Dec | O15: 0.13076195
A16: Grand Total | B16: 2297200.9 | D16: Grand Total | E16: 286397.02 | G16: Grand Total | H16: 37873 | K16: Grand Total | L16: 9994 | N16: Grand Total | O16: 0.12467217
B17: =GETPIVOTDATA("[Measures].[Sum of Sales]",$A$3) -> 2297200.9 | E17: =GETPIVOTDATA("[Measures].[Sum of Profit]",$D$3) -> 286397.02 | H17: =GETPIVOTDATA("[Measures].[Sum of Quantity]",$G$3) -> 37873 | L17: =GETPIVOTDATA("[Measures].[Count of Order ID]",$K$3) -> 9994 | O17: =GETPIVOTDATA("[Measures].[profit margin]",$N$3) -> 0.12467217

Sheet analysis
A2: Row Labels | B2: Sum of Sales | D2: Row Labels | E2: Count of Order ID | G2: Row Labels | H2: Sum of Profit | K2: Row Labels | L2: Sum of Sales | M2: Sum of Profit | Z2: Row Labels | AA2: Sum of Profit | AC2: CATEGORY | AD2: PROFIT | AG2: Row Labels | AH2: Sum of Sales | AL2: Row Labels | AM2: Sum of Sales
A3: Central | B3: 501239.89 | D3: 2011 | E3: 1993 | G3: Furniture | H3: 18451.273 | K3: Jan | L3: 95365.938 | M3: 9199.27 | Z3: Furniture | AA3: 18451.273 | AC3: =Z3 -> Furniture | AD3: =GETPIVOTDATA("[Measures].[Sum of Profit]",$Z$2,"[Table_1].[Category]","[Table_1].[Category].&[Furniture]") -> 18451.273 | AG3: Furniture | AH3: 0.32300171 | AL3: Alabama | AM3: 19510.64 | AO3: STATE | AP3: SALES | AV3: Row Labels | AW3: Sum of Sales
A4: East | B4: 678781.24 | D4: 2012 | E4: 2102 | G4: Office Supplies | H4: 122490.8 | K4: Feb | L4: 60172.649 | M4: 10288.899 | Z4: Office Supplies | AA4: 122490.8 | AC4: =Z4 -> Office Supplies | AD4: =GETPIVOTDATA("[Measures].[Sum of Profit]",$Z$2,"[Table_1].[Category]","[Table_1].[Category].&[Office Supplies]") -> 122490.8 | AG4: Office Supplies | AH4: 0.31301008 | AL4: Arizona | AM4: 35282.001 | AO4: =AL3 -> Alabama | AP4: 19510.64 | AV4: Binders | AW4: 203412.73
A5: South | B5: 391721.91 | D5: 2013 | E5: 2580 | G5: Technology | H5: 145454.95 | K5: Mar | L5: 199252.98 | M5: 26806.574 | Z5: Technology | AA5: 145454.95 | AC5: =Z5 -> Technology | AD5: =GETPIVOTDATA("[Measures].[Sum of Profit]",$Z$2,"[Table_1].[Category]","[Table_1].[Category].&[Technology]") -> 145454.95 | AG5: Technology | AH5: 0.36398821 | AL5: Arkansas | AM5: 11678.13 | AO5: =AL4 -> Arizona | AP5: 35282.001 | AV5: Tables | AW5: 206965.53
A6: West | B6: 725457.82 | D6: 2014 | E6: 3319 | K6: Apr | L6: 141851.57 | M6: 13437.807 | AC6: GRAND TOTAL | AD6: =SUM(AD3:AD5) -> 286397.02 | AL6: California | AM6: 457687.63 | AO6: =AL5 -> Arkansas | AP6: 11678.13 | AV6: Storage | AW6: 223843.61
K7: May | L7: 156122.29 | M7: 22308.513 | AL7: Colorado | AM7: 32108.118 | AO7: =AL6 -> California | AP7: 457687.63 | AV7: Chairs | AW7: 328449.1
K8: Jun | L8: 147082.61 | M8: 20899.335 | AL8: Connecticut | AM8: 13384.357 | AO8: =AL7 -> Colorado | AP8: 32108.118 | AV8: Phones | AW8: 330007.05 | AZ8: Sum of Profit
K9: Jul | L9: 149580.84 | M9: 13535.383 | AL9: Delaware | AM9: 27451.069 | AO9: =AL8 -> Connecticut | AP9: 13384.357 | AZ9: 286397.02
K10: Aug | L10: 159589.45 | M10: 21896.715 | AL10: District of Columbia | AM10: 2865.02 | AO10: =AL9 -> Delaware | AP10: 27451.069
K11: Sep | L11: 309770.1 | M11: 37293.193 | AL11: Florida | AM11: 89473.708 | AO11: =AL10 -> District of Columbia | AP11: 2865.02
K12: Oct | L12: 197115.2 | M12: 31469.664 | AL12: Georgia | AM12: 49095.84 | AO12: =AL11 -> Florida | AP12: 89473.708
K13: Nov | L13: 349120.07 | M13: 35825.537 | AL13: Idaho | AM13: 4382.486 | AO13: =AL12 -> Georgia | AP13: 49095.84
K14: Dec | L14: 332177.16 | M14: 43436.134 | AL14: Illinois | AM14: 80166.101 | AO14: =AL13 -> Idaho | AP14: 4382.486
AL15: Indiana | AM15: 53555.36 | AO15: =AL14 -> Illinois | AP15: 80166.101
AL16: Iowa | AM16: 4579.76 | AO16: =AL15 -> Indiana | AP16: 53555.36
AL17: Kansas | AM17: 2914.31 | AO17: =AL16 -> Iowa | AP17: 4579.76
AL18: Kentucky | AM18: 36591.75 | AO18: =AL17 -> Kansas | AP18: 2914.31
AL19: Louisiana | AM19: 9217.03 | AO19: =AL18 -> Kentucky | AP19: 36591.75
AL20: Maine | AM20: 1270.53 | AO20: =AL19 -> Louisiana | AP20: 9217.03
AL21: Maryland | AM21: 23705.523 | AO21: =AL20 -> Maine | AP21: 1270.53
AL22: Massachusetts | AM22: 28634.434 | AO22: =AL21 -> Maryland | AP22: 23705.523
AL23: Michigan | AM23: 76269.614 | AO23: =AL22 -> Massachusetts | AP23: 28634.434
AL24: Minnesota | AM24: 29863.15 | AO24: =AL23 -> Michigan | AP24: 76269.614
AL25: Mississippi | AM25: 10771.34 | AO25: =AL24 -> Minnesota | AP25: 29863.15
AL26: Missouri | AM26: 22205.15 | AO26: =AL25 -> Mississippi | AP26: 10771.34
... AL51: Wyoming | AM51: 1603.136 | AO51: =AL50 -> Wisconsin | AP51: 32114.61
AO52: =AL51 -> Wyoming | AP52: 1603.136

Sheet Dashboard
